Metadata-Version: 2.1
Name: stringf
Version: 0.0.7
Summary: Functions for strings and lists
Author: Mathdallas_code(Jaiwant Morampudi)
Author-email: <krishnapacs255@gmail.com>
Keywords: python,string,English,words,functions
Classifier: Development Status :: 1 - Planning
Classifier: Intended Audience :: Developers
Classifier: Programming Language :: Python :: 3
Classifier: Operating System :: Unix
Classifier: Operating System :: MacOS :: MacOS X
Classifier: Operating System :: Microsoft :: Windows
